monitor_app/__init__.py
monitor_app/app.py
monitor_app/cli.py
monitor_app/config/config.py
monitor_app/csv/data.csv
monitor_app/csv/orders.csv
monitor_app/csv/products.csv
monitor_app/csv/users.csv
monitor_app/csv_to_db.py
monitor_app/instances/database.db
monitor_app/static/css/bootstrap.min.css
monitor_app/static/css/jquery.datatables.min.css
monitor_app/static/favicon.ico
monitor_app/static/img/background.webp
monitor_app/static/img/logo.webp
monitor_app/static/js/bootstrap.bundle.min.js
monitor_app/static/js/jquery.datatables.min.js
monitor_app/static/js/jquery.min.js
monitor_app/static/js/refresh_table.js
monitor_app/templates/base.html
monitor_app/templates/index.html
monitor_app/templates/table.html
monitor_app-0.1.9.dist-info/LICENSE
monitor_app-0.1.9.dist-info/METADATA
monitor_app-0.1.9.dist-info/WHEEL
monitor_app-0.1.9.dist-info/entry_points.txt
monitor_app-0.1.9.dist-info/RECORD
