Metadata-Version: 2.1
Name: monitor-app
Version: 0.1.9
Summary: A simple Flask-based database viewer and manager
Home-page: https://github.com/hardwork9047/monitor-app
License: MIT
Author: hardwork9047
Author-email: tomatosimple1104@gmail.com
Requires-Python: >=3.10,<4.0
Classifier: License :: OSI Approved :: MIT License
Classifier: Programming Language :: Python :: 3
Classifier: Programming Language :: Python :: 3.10
Classifier: Programming Language :: Python :: 3.11
Classifier: Programming Language :: Python :: 3.12
Classifier: Programming Language :: Python :: 3.13
Requires-Dist: click (>=8.1.3,<9.0.0)
Requires-Dist: flasgger (>=0.9.7.1,<0.10.0.0)
Requires-Dist: flask (>=3.1.0,<4.0.0)
Requires-Dist: flask-cors (>=4.0.0,<5.0.0)
Requires-Dist: flask-sqlalchemy (>=3.1.1,<4.0.0)
Requires-Dist: pandas (>=2.2.3,<3.0.0)
Requires-Dist: pg8000 (>=1.30.5,<2.0.0)
Requires-Dist: pymysql (>=1.1.0,<2.0.0)
Requires-Dist: toml (>=0.10.2,<0.11.0)
Project-URL: Documentation, https://github.com/hardwork9047/monitor-app
Project-URL: Repository, https://github.com/hardwork9047/monitor-app
